MANIFEST.in
README.txt
setup.py
archetypes/__init__.py
archetypes.kss.egg-info/PKG-INFO
archetypes.kss.egg-info/SOURCES.txt
archetypes.kss.egg-info/dependency_links.txt
archetypes.kss.egg-info/namespace_packages.txt
archetypes.kss.egg-info/not-zip-safe
archetypes.kss.egg-info/requires.txt
archetypes.kss.egg-info/top_level.txt
archetypes/kss/__init__.py
archetypes/kss/config.py
archetypes/kss/configure.zcml
archetypes/kss/events.py
archetypes/kss/fields.py
archetypes/kss/fields_versioning.py
archetypes/kss/interfaces.py
archetypes/kss/utils.py
archetypes/kss/validation.py
archetypes/kss/browser/edit_field_wrapper.pt
archetypes/kss/browser/view_field_wrapper.pt
archetypes/kss/commands/__init__.py
archetypes/kss/commands/configure.zcml
archetypes/kss/commands/interfaces.py
archetypes/kss/commands/validation.py
archetypes/kss/tests/__init__.py
archetypes/kss/tests/test_events.py
archetypes/kss/tests/test_fields.py
archetypes/kss/tests/test_validation.py
archetypes/kss/tests/selenium_tests/plone_inline_editing.html
docs/HISTORY.txt
docs/LICENSE.GPL
docs/LICENSE.txt