Metadata-Version: 1.0
Name: archetypes.kss
Version: 1.7.3
Summary: KSS (Kinetic Style Sheets) for Archetypes
Home-page: http://plone.org
Author: Plone Foundation
Author-email: plone-developers@lists.sourceforge.net
License: GPL
Platform: UNKNOWN
Classifier: Framework :: Plone
Classifier: Framework :: Zope2
Classifier: Programming Language :: Python
